{
"type": "FeatureCollection",
"crs": { "type": "name", "properties": { "name": "urn:ogc:def:crs:OGC:1.3:CRS84" } },
"features": [
{ "type": "Feature", "properties": { "id": "ak16994519", "cases": 10, "date": "2020-05-16", "country": "PL" }, "geometry": { "type": "Point", "coordinates": [ 19.145136, 51.919438 ] } },
{ "type": "Feature", "properties": { "id": "ak16994517", "cases": 5, "date": "2020-05-16", "country": "GER" }, "geometry": { "type": "Point", "coordinates": [ 10.4541194, 51.1642292 ] } },
{ "type": "Feature", "properties": { "id": "akx6994517", "cases": 4, "date": "2020-05-16", "country": "GER" }, "geometry": { "type": "Point", "coordinates": [ 11, 49.1642292 ] } }
]
}
